{
  "pedidos": [
    {
      "id": "f294",
      "title": "Fone de Ouvido Bluetooth",
      "imageUri": "https://www.eletronicafaria.com.br/3889-large_default/fone-de-ouvido-bluetooth-airdots-2-xiaomi.jpg",
      "content": "Qualidade de som incrível",
      "status": "Em andamento"
    },
    {
      "id": "2175",
      "title": "iPhone 14 Pro",
      "imageUri": "https://lwcenter.com.br/wp-content/uploads/2023/02/14-branco.png",
      "content": "Apple",
      "status": "Em andamento"
    }
  ],
  "pedidosConfirmados": [
    {
      "id": "92bf",
      "title": "Samsung S24 Ultra",
      "imageUri": "https://images.samsung.com/is/image/samsung/p6pim/pt/2401/gallery/pt-galaxy-s24-s928-489596-sm-s928bzoheub-539355002?$650_519_PNG$",
      "content": "Samsung",
      "status": "Confirmado"
    },
    {
      "id": "438d",
      "title": "iPhone 14 Pro",
      "imageUri": "https://lwcenter.com.br/wp-content/uploads/2023/02/14-branco.png",
      "content": "Apple",
      "status": "Confirmado"
    }
  ],
  "users": [
    {
      "name": "Emersinho",
      "phone": "11 98765-4321",
      "profileImage": "https://www.esportelandia.com.br/wp-content/uploads/2024/05/Dwaney-Johnson-The-Rock-Mark-Kerr.png",
      "id": "08cf"
    },
    {
      "name": "Kawan Wig",
      "phone": "323213",
      "profileImage": "https://upload.wikimedia.org/wikipedia/commons/thumb/7/7a/LeBron_James_%2851959977144%29_%28cropped2%29.jpg/640px-LeBron_James_%2851959977144%29_%28cropped2%29.jpg",
      "id": "c073"
    },
    {
      "name": "Emersinho Jr",
      "phone": "118786868879",
      "profileImage": "https://www.esportelandia.com.br/wp-content/uploads/2024/05/Dwaney-Johnson-The-Rock-Mark-Kerr.png",
      "id": "5dce"
    },
    {
      "id": "c7ae",
      "name": "Ricks",
      "phone": "11 98987-9789",
      "email": "teste@gmail.com",
      "password": "123",
      "profileImage": "https://www.esportelandia.com.br/wp-content/uploads/2024/05/Dwaney-Johnson-The-Rock-Mark-Kerr.png"
    }
  ]
}